cast_vue/__init__.py
cast_vue/apps.py
cast_vue/static/cast_vue/main-LYJpxvC7.js
cast_vue/static/cast_vue/main-bbP4tSv_.css
cast_vue/static/cast_vue/manifest.json
cast_vue/static/cast_vue/.vite/manifest.json
cast_vue/static/src/css/cast_vue/pygments.css
cast_vue/static/src/css/cast_vue/styles.css
cast_vue/static/src/js/cast_vue/App.vue
cast_vue/static/src/js/cast_vue/config.ts
cast_vue/static/src/js/cast_vue/env.d.ts
cast_vue/static/src/js/cast_vue/main.ts
cast_vue/static/src/js/cast_vue/components/CommentForm.vue
cast_vue/static/src/js/cast_vue/components/CommentItem.vue
cast_vue/static/src/js/cast_vue/components/CommentList.vue
cast_vue/static/src/js/cast_vue/components/FilterForm.vue
cast_vue/static/src/js/cast_vue/components/LoadPostList.vue
cast_vue/static/src/js/cast_vue/components/PaginationButtons.vue
cast_vue/static/src/js/cast_vue/components/PodlovePlayer.vue
cast_vue/static/src/js/cast_vue/components/PostDetail.vue
cast_vue/static/src/js/cast_vue/components/PostItem.vue
cast_vue/static/src/js/cast_vue/components/PostList.vue
cast_vue/static/src/js/cast_vue/components/SelectTheme.vue
cast_vue/static/src/js/cast_vue/components/types.ts
cast_vue/static/src/js/cast_vue/helpers/url.ts
cast_vue/static/src/js/cast_vue/stores/dataStore.ts
cast_vue/static/src/tests/CommentItem.test.ts
cast_vue/static/src/tests/CommentList.test.ts
cast_vue/static/src/tests/calculator.test.ts
cast_vue/templates/cast/vue/400.html
cast_vue/templates/cast/vue/403.html
cast_vue/templates/cast/vue/403_csrf.html
cast_vue/templates/cast/vue/404.html
cast_vue/templates/cast/vue/500.html
cast_vue/templates/cast/vue/_filter_form.html
cast_vue/templates/cast/vue/_list_of_posts_and_paging_controls.html
cast_vue/templates/cast/vue/base.html
cast_vue/templates/cast/vue/blog_list_of_posts.html
cast_vue/templates/cast/vue/blog_list_of_posts_old.html
cast_vue/templates/cast/vue/episode.html
cast_vue/templates/cast/vue/gallery.html
cast_vue/templates/cast/vue/gallery_htmx.html
cast_vue-0.0.25.dist-info/LICENSE
cast_vue-0.0.25.dist-info/WHEEL
cast_vue-0.0.25.dist-info/METADATA
cast_vue-0.0.25.dist-info/RECORD
