Metadata-Version: 2.1
Name: cast-vue
Version: 0.0.25
Summary: Vue theme for django-cast.
Keywords: blog,podcast,video,audio
Author-email: Jochen Wersdörfer <jochen-castvue@wersdoerfer.de>
Requires-Python: >=3.9
Classifier: Environment :: Web Environment
Classifier: Framework :: Django
Classifier: Framework :: Django :: 4.1
Classifier: Framework :: Django :: 4.2
Classifier: Framework :: Django :: 5.0
Classifier: Intended Audience :: Developers
Classifier: License :: OSI Approved :: BSD License
Classifier: Topic :: Internet
Classifier: Development Status :: 3 - Alpha
Classifier: Environment :: Web Environment
Classifier: License :: OSI Approved :: MIT License
Classifier: Programming Language :: Python :: 3 :: Only
Classifier: Programming Language :: Python :: 3.10
Classifier: Programming Language :: Python :: 3.11
Classifier: Programming Language :: Python :: 3.12
Classifier: Topic :: Internet :: WWW/HTTP
Classifier: Topic :: Internet :: WWW/HTTP :: Dynamic Content
Requires-Dist: django-cast
Requires-Dist: django-vite
Requires-Dist: black ; extra == "dev"
Requires-Dist: flake8 ; extra == "dev"
Requires-Dist: django-environ ; extra == "dev"
Requires-Dist: django_extensions ; extra == "dev"
Requires-Dist: django-stubs[compatible-mypy] ; extra == "dev"
Requires-Dist: isort ; extra == "dev"
Requires-Dist: jupyter ; extra == "dev"
Requires-Dist: mypy ; extra == "dev"
Requires-Dist: rich ; extra == "dev"
Requires-Dist: tox ; extra == "dev"
Requires-Dist: typer ; extra == "dev"
Requires-Dist: furo ; extra == "doc"
Requires-Dist: pytest >= 6 ; extra == "test"
Requires-Dist: pytest-cov >= 3 ; extra == "test"
Requires-Dist: pytest-django ; extra == "test"
Requires-Dist: pytest-mock ; extra == "test"
Project-URL: Documentation, https://cast-vue.readthedocs.io/en/latest/
Project-URL: Source, https://github.com/ephes/cast-vue
Provides-Extra: dev
Provides-Extra: doc
Provides-Extra: test
